examples/__init__.py
examples/acquire/__init__.py
examples/acquire/save_camera_feeds.py
sksurgeryimage/__init__.py
sksurgeryimage/_version.py
sksurgeryimage/acquire/__init__.py
sksurgeryimage/acquire/stereo_video.py
sksurgeryimage/acquire/video_source.py
sksurgeryimage/acquire/video_writer.py
sksurgeryimage/calibration/__init__.py
sksurgeryimage/calibration/charuco.py
sksurgeryimage/display/__init__.py
sksurgeryimage/display/identify_cameras.py
sksurgeryimage/processing/__init__.py
sksurgeryimage/processing/aruco_point_detector.py
sksurgeryimage/processing/charuco_point_detector.py
sksurgeryimage/processing/chessboard_point_detector.py
sksurgeryimage/processing/dotty_grid_point_detector.py
sksurgeryimage/processing/interlace.py
sksurgeryimage/processing/morphological_operators.py
sksurgeryimage/processing/point_detector.py
sksurgeryimage/ui/ImageCropper.py
sksurgeryimage/ui/__init__.py
sksurgeryimage/utilities/__init__.py
sksurgeryimage/utilities/camera_utilities.py
sksurgeryimage/utilities/utilities.py
sksurgeryimage/utilities/weisslogo.py
tests/processing/__init__.py
tests/processing/conftest.py
tests/processing/test_aruco_point_detector.py
tests/processing/test_charuco_point_detector.py
tests/processing/test_chessboard_point_detector.py
tests/processing/test_deinterlace.py
tests/processing/test_dotty_grid_detector_metal.py
tests/processing/test_dotty_grid_point_detector.py
tests/processing/test_dotty_grid_utils.py
tests/processing/test_interlace.py
tests/processing/test_morphological_operators.py
tests/processing/test_point_detector.py
tests/processing/test_rectification.py
tests/processing/test_stack_destack.py
tests/processing/test_undistortion.py
tests/processing/test_validate_size.py
scikit_surgeryimage-0.6.4.dist-info/LICENSE
scikit_surgeryimage-0.6.4.dist-info/METADATA
scikit_surgeryimage-0.6.4.dist-info/WHEEL
scikit_surgeryimage-0.6.4.dist-info/entry_points.txt
scikit_surgeryimage-0.6.4.dist-info/top_level.txt
scikit_surgeryimage-0.6.4.dist-info/RECORD
