Metadata-Version: 2.1
Name: scikit-surgeryimage
Version: 0.6.4
Summary: scikit-surgeryimage implements image processing tools and alogrithms for Image Guided Surgery.
Home-page: https://weisslab.cs.ucl.ac.uk/WEISS/SoftwareRepositories/SNAPPY/scikit-surgeryimage
Author: Matt Clarkson
Author-email: YOUR-EMAIL@ucl.ac.uk
License: BSD-3 license
Keywords: medical imaging
Platform: UNKNOWN
Classifier: Development Status :: 3 - Alpha
Classifier: Intended Audience :: Developers
Classifier: Intended Audience :: Healthcare Industry
Classifier: Intended Audience :: Information Technology
Classifier: Intended Audience :: Science/Research
Classifier: License :: OSI Approved :: BSD License
Classifier: Programming Language :: Python
Classifier: Programming Language :: Python :: 2
Classifier: Programming Language :: Python :: 3
Classifier: Topic :: Scientific/Engineering :: Information Analysis
Classifier: Topic :: Scientific/Engineering :: Medical Science Apps.
Requires-Dist: six (>=1.10)
Requires-Dist: numpy (>=1.11)
Requires-Dist: opencv-contrib-python (>=4.1.1.26)
Requires-Dist: scikit-surgerycore (>=0.1.0)
